ailabs_asr/__init__.py
ailabs_asr/api.py
ailabs_asr/client.py
ailabs_asr/streaming.py
ailabs_asr/transcriber.py
ailabs_asr/types.py
ailabs_asr/clients/ASRResultHandleStrategy.py
ailabs_asr/clients/AbstractWebsocketClient.py
ailabs_asr/clients/WebSocketClient.py
ailabs_asr/clients/__init__.py
ailabs_asr/configs/api.yaml
ailabs_asr-0.1.0.dist-info/LICENSE
ailabs_asr-0.1.0.dist-info/METADATA
ailabs_asr-0.1.0.dist-info/WHEEL
ailabs_asr-0.1.0.dist-info/top_level.txt
ailabs_asr-0.1.0.dist-info/RECORD
