Metadata-Version: 2.1
Name: ailabs-asr
Version: 0.1.0
Summary: Package to utilize the speech to text API powered by AILabs.tw
Home-page: https://github.com/TaiwanAILabs-Yating/asr-python-sdk
Author: Hendryboyz
Author-email: Hendry.js1247@gmail.com
License: UNKNOWN
Platform: UNKNOWN
Classifier: Programming Language :: Python :: 3.9
Classifier: License :: OSI Approved :: GNU General Public License v3 (GPLv3)
License-File: LICENSE
Requires-Dist: PyYAML (>=6.0)
Requires-Dist: requests (>=2.28.0)
Requires-Dist: PyAudio (>=0.2.11)
Requires-Dist: websocket-client (>=1.3.2)
